LICENSE.rst
MANIFEST.in
README.rst
setup.py
mezzanine_slides/__init__.py
mezzanine_slides/admin.py
mezzanine_slides/models.py
mezzanine_slides.egg-info/PKG-INFO
mezzanine_slides.egg-info/SOURCES.txt
mezzanine_slides.egg-info/dependency_links.txt
mezzanine_slides.egg-info/not-zip-safe
mezzanine_slides.egg-info/requires.txt
mezzanine_slides.egg-info/top_level.txt
mezzanine_slides/static/responsiveslides/responsiveslides.css
mezzanine_slides/static/responsiveslides/responsiveslides.js
mezzanine_slides/static/vegas/jquery.vegas.min.css
mezzanine_slides/static/vegas/jquery.vegas.min.js
mezzanine_slides/static/vegas/images/loading.gif
mezzanine_slides/templates/includes/fullscreen_slides.html
mezzanine_slides/templates/includes/standard_slides.html