Metadata-Version: 1.1
Name: mezzanine-slides
Version: 2.0.1
Summary: Easily plug a slideshow into your mezzanine website on all pages.
Home-page: http://github.com/overshard/mezzanine-slides
Author: Isaac Bythewood
Author-email: isaac@bythewood.me
License: Simplified BSD
Download-URL: http://github.com/overshard/mezzanine-slides/downloads
Platform: UNKNOWN
Classifier: Development Status :: 5 - Production/Stable
Classifier: Environment :: Web Environment
Classifier: Intended Audience :: Developers
Classifier: License :: OSI Approved :: BSD License
Classifier: Operating System :: OS Independent
Classifier: Programming Language :: Python
Classifier: Framework :: Django
